pixel_planner/__init__.py
pixel_planner/__main__.py
pixel_planner/cli.py
pixel_planner/templates/pixel-planner-phase-template.md
pixel_planner-0.2.2.dist-info/licenses/LICENSE
pixel_planner-0.2.2.dist-info/licenses/NOTICE
pixel_planner-0.2.2.dist-info/METADATA
pixel_planner-0.2.2.dist-info/WHEEL
pixel_planner-0.2.2.dist-info/entry_points.txt
pixel_planner-0.2.2.dist-info/top_level.txt
pixel_planner-0.2.2.dist-info/RECORD
