Metadata-Version: 2.4
Name: pixel-planner
Version: 0.2.2
Summary: Automate project plans written in Markdown
Author-email: Ivan Nagy <786743+ivannagy@users.noreply.github.com>
Project-URL: Homepage, https://github.com/ivannagy/pixel-planner
Project-URL: Bug Reports, https://github.com/ivannagy/pixel-planner/issues
Project-URL: Source, https://github.com/ivannagy/pixel-planner
Keywords: markdown,project-management,gantt,timeline,planning
Classifier: Development Status :: 3 - Alpha
Classifier: Intended Audience :: Developers
Classifier: License :: OSI Approved :: Apache Software License
Classifier: Operating System :: OS Independent
Classifier: Programming Language :: Python :: 3
Classifier: Programming Language :: Python :: 3.9
Classifier: Programming Language :: Python :: 3.10
Classifier: Programming Language :: Python :: 3.11
Classifier: Programming Language :: Python :: 3.12
Classifier: Topic :: Office/Business :: Scheduling
Classifier: Topic :: Software Development :: Documentation
Classifier: Topic :: Text Processing :: Markup
Requires-Python: >=3.9
License-File: LICENSE
License-File: NOTICE
Dynamic: license-file
